bma_cli/__init__.py
bma_cli/bma_cli.py
bma_cli-0.9.2.dist-info/licenses/LICENSE
bma_cli-0.9.2.dist-info/METADATA
bma_cli-0.9.2.dist-info/WHEEL
bma_cli-0.9.2.dist-info/entry_points.txt
bma_cli-0.9.2.dist-info/top_level.txt
bma_cli-0.9.2.dist-info/RECORD
