Metadata-Version: 2.4
Name: bma-cli
Version: 0.9.2
Summary: BornHack Media Archive CLI Tool
Author: Thomas Steen Rasmussen
Author-email: thomas@gibfest.dk
Project-URL: homepage, https://github.com/bornhack/bma-cli-python
Classifier: Programming Language :: Python :: 3
Classifier: Operating System :: OS Independent
Requires-Python: >=3.11
License-File: LICENSE
Requires-Dist: typer-slim==0.12.5
Requires-Dist: bma-client-lib>=0.12.0
Provides-Extra: dev
Requires-Dist: pre-commit==4.0.0; extra == "dev"
Requires-Dist: setuptools-scm==8.0.4; extra == "dev"
Dynamic: license-file
